fabricatio_locale-0.1.6.dist-info/METADATA
fabricatio_locale-0.1.6.dist-info/WHEEL
fabricatio_locale-0.1.6.dist-info/licenses/LICENSE
fabricatio_locale/__init__.py
fabricatio_locale/actions/__init__.py
fabricatio_locale/actions/localize.py
fabricatio_locale/capabilities/__init__.py
fabricatio_locale/capabilities/localize.py
fabricatio_locale/config.py
fabricatio_locale/models/__init__.py
fabricatio_locale/py.typed
fabricatio_locale/rust.cpython-313-x86_64-linux-gnu.so
fabricatio_locale/rust.pyi
fabricatio_locale/workflows/__init__.py
fabricatio_locale-0.1.6.dist-info/RECORD
