Metadata-Version: 2.4
Name: fabricatio-locale
Version: 0.1.6
Requires-Dist: fabricatio-core
Requires-Dist: fabricatio-translate
License-File: LICENSE
Summary: An extension of fabricatio, which brings up the capability to generate locolization based on po file.
Author-email: Whth <zettainspector@foxmail.com>
Requires-Python: >=3.12, <3.15
Project-URL: Homepage, https://github.com/Whth/fabricatio
Project-URL: Repository, https://github.com/Whth/fabricatio
Project-URL: Issues, https://github.com/Whth/fabricatio/issues
